alpaqa-0.0.1.dist-info/LICENSE
alpaqa-0.0.1.dist-info/METADATA
alpaqa-0.0.1.dist-info/top_level.txt
alpaqa-0.0.1.dist-info/WHEEL
alpaqa-0.0.1.dist-info/RECORD
alpaqa/casadi_problem.py
alpaqa/_alpaqa.so
alpaqa/test.py
alpaqa/__init__.pyi
alpaqa/__init__.py
alpaqa/casadi_problem.pyi
alpaqa/_alpaqa.pyi
