Metadata-Version: 2.1
Name: alpaqa
Version: 0.0.1
Summary: Augmented Lagrangian and PANOC solvers for nonconvex numerical optimization
Home-page: https://github.com/kul-optec/alpaqa
Author: Pieter P
Author-email: 
License: UNKNOWN
Project-URL: Documentation, https://kul-optec.github.io/alpaqa
Project-URL: Source, https://github.com/kul-optec/alpaqa
Project-URL: Bug Tracker, https://github.com/kul-optec/alpaqa/issues
Keywords: optimization
Platform: UNKNOWN
Classifier: Development Status :: 3 - Alpha
Classifier: Intended Audience :: Science/Research
Classifier: Topic :: Scientific/Engineering
Classifier: License :: OSI Approved :: GNU Lesser General Public License v3 (LGPLv3)
Classifier: Programming Language :: Python :: 3
Classifier: Programming Language :: Python :: 3.7
Classifier: Programming Language :: Python :: 3.8
Classifier: Programming Language :: Python :: 3.9
Classifier: Programming Language :: Python :: 3.10
Classifier: Operating System :: POSIX :: Linux
Classifier: Operating System :: Microsoft :: Windows
Requires-Python: >=3.7
License-File: LICENSE
Requires-Dist: numpy
Requires-Dist: casadi
Requires-Dist: ninja
Requires-Dist: cmake
